profile_python/__init__.py
profile_python/__main__.py
profile_python/app.py
profile_python/endpoint.py
profile_python/networking.py
profile_python/profile.py
profile_python-0.4.0.dist-info/LICENSE
profile_python-0.4.0.dist-info/METADATA
profile_python-0.4.0.dist-info/WHEEL
profile_python-0.4.0.dist-info/entry_points.txt
profile_python-0.4.0.dist-info/RECORD
