Metadata-Version: 2.1
Name: profile-python
Version: 0.4.0
Summary: Profile python is a script for you to view your data and github repositories.
Home-page: https://github.com/heroesofcode/profile-python
License: MIT
Author: João Lucas
Author-email: joaolucasfp2001@gmail.com
Requires-Python: >=3.8,<4.0
Classifier: Environment :: Console
Classifier: License :: OSI Approved :: MIT License
Classifier: Operating System :: OS Independent
Classifier: Programming Language :: Python :: 3
Classifier: Programming Language :: Python :: 3.8
Classifier: Programming Language :: Python :: 3.9
Classifier: Programming Language :: Python :: 3.10
Classifier: Programming Language :: Python :: 3.11
Requires-Dist: flake8 (>=4.0.1,<6.0.0)
Requires-Dist: pyfiglet (>=0.8.post1,<0.9)
Requires-Dist: pytest-cov (>=3,<5)
Requires-Dist: requests (>=2.27.1,<3.0.0)
Requires-Dist: rich (>=12.4.1,<14.0.0)
Project-URL: Repository, https://github.com/heroesofcode/profile-python
